jumpstarter_driver_snmp/__init__.py
jumpstarter_driver_snmp/client.py
jumpstarter_driver_snmp/driver.py
jumpstarter_driver_snmp/driver_test.py
jumpstarter_driver_snmp-0.7.4.dist-info/METADATA
jumpstarter_driver_snmp-0.7.4.dist-info/WHEEL
jumpstarter_driver_snmp-0.7.4.dist-info/RECORD
